codo/__init__.py
codo/main.py
codo_python-1.0.4.dist-info/LICENSE
codo_python-1.0.4.dist-info/METADATA
codo_python-1.0.4.dist-info/WHEEL
codo_python-1.0.4.dist-info/top_level.txt
codo_python-1.0.4.dist-info/RECORD
