Metadata-Version: 2.2
Name: codo-python
Version: 1.0.4
Summary: (C)ompute (O)perations in (D)ependency (O)rder
License-File: LICENSE
